{
    "A0001": {
        "patient_id": "P0001",
        "doctor_id": "D0001",
        "slot_id": 3,
        "appointment_time": "11:30",
        "status": "confirmed",
        "created_at": "2026-01-24T03:04:17.619340",
        "confirmed_at": "2026-01-24T03:04:29.574303",
        "thread_id": 8614128704,
        "thread_name": "MainThread"
    },
    "A0002": {
        "patient_id": "P0001",
        "doctor_id": "D0001",
        "slot_id": 4,
        "appointment_time": "12:00",
        "status": "confirmed",
        "created_at": "2026-01-24T14:09:14.345942",
        "confirmed_at": "2026-01-24T14:09:27.726019",
        "thread_id": 8614128704,
        "thread_name": "MainThread"
    },
    "A0003": {
        "patient_id": "P0001",
        "doctor_id": "D0001",
        "slot_id": 1,
        "appointment_time": "10:30",
        "status": "confirmed",
        "created_at": "2026-01-24T14:12:51.802505",
        "confirmed_at": "2026-01-24T14:13:09.248673",
        "thread_id": 8614128704,
        "thread_name": "MainThread"
    },
    "A0004": {
        "patient_id": "P0001",
        "doctor_id": "D0001",
        "slot_id": 1,
        "appointment_time": "10:30",
        "status": "confirmed",
        "created_at": "2026-01-24T15:33:43.160844",
        "confirmed_at": "2026-01-24T15:34:09.029319",
        "thread_id": 8614128704,
        "thread_name": "MainThread"
    }
}